streamlit_faker/__init__.py
streamlit_faker/chart.py
streamlit_faker/common.py
streamlit_faker/data_display.py
streamlit_faker/input.py
streamlit_faker/media.py
streamlit_faker/status.py
streamlit_faker/text.py
streamlit_faker-0.0.3.dist-info/LICENSE.md
streamlit_faker-0.0.3.dist-info/METADATA
streamlit_faker-0.0.3.dist-info/WHEEL
streamlit_faker-0.0.3.dist-info/top_level.txt
streamlit_faker-0.0.3.dist-info/RECORD
