Metadata-Version: 2.1
Name: streamlit_faker
Version: 0.0.3
Summary: streamlit-faker is a library to very easily fake Streamlit commands
Author-email: Arnaud Miribel <arnaudmiribel@gmail.com>
Project-URL: Homepage, https://github.com/arnaudmiribel/streamlit-faker
Project-URL: Bug Tracker, https://github.com/arnaudmiribel/streamlit-faker/issues
Keywords: python,streamlit,faker
Classifier: Programming Language :: Python :: 3
Requires-Python: >=3.6
License-File: LICENSE.md
Requires-Dist: streamlit
Requires-Dist: streamlit-extras
Requires-Dist: faker
Requires-Dist: matplotlib
